{
  "microcat_categories": 318,
  "train_samples": 5000,
  "columns": [
    "title",
    "description",
    "microcat_id",
    "real_weight",
    "real_height",
    "real_length",
    "real_width",
    "path",
    "mean_weight",
    "std_weight",
    "mean_height",
    "std_height",
    "mean_length",
    "std_length",
    "mean_width",
    "std_width"
  ],
  "data_types": "{'title': dtype('O'), 'description': dtype('O'), 'microcat_id': dtype('int64'), 'real_weight': dtype('float64'), 'real_height': dtype('float64'), 'real_length': dtype('float64'), 'real_width': dtype('float64'), 'path': dtype('O'), 'mean_weight': dtype('float64'), 'std_weight': dtype('float64'), 'mean_height': dtype('float64'), 'std_height': dtype('float64'), 'mean_length': dtype('float64'), 'std_length': dtype('float64'), 'mean_width': dtype('float64'), 'std_width': dtype('float64')}",
  "test_samples": 5000
}